README.rst
motop
setup.py
libmotop/Console.py
libmotop/Motop.py
libmotop/QueryScreen.py
libmotop/Server.py
libmotop/__init__.py
libmotop/console.py
libmotop/motop.py
libmotop/queryscreen.py
libmotop/server.py
motop.egg-info/PKG-INFO
motop.egg-info/SOURCES.txt
motop.egg-info/dependency_links.txt
motop.egg-info/requires.txt
motop.egg-info/top_level.txt