Metadata-Version: 1.0
Name: motop
Version: 3.1
Summary: "Top" clone for MongoDB.
Home-page: https://github.com/tart/motop
Author: Emre Hasegeli
Author-email: hasegeli@tart.com.tr
License: ICS
Keywords: mongo realtime monitoring examine explain kill operations
Platform: POSIX
